siege_engine/__init__.py
siege_engine/__main__.py
siege_engine/operate.py
siege_engine-3.0.dist-info/LICENSE
siege_engine-3.0.dist-info/METADATA
siege_engine-3.0.dist-info/WHEEL
siege_engine-3.0.dist-info/top_level.txt
siege_engine-3.0.dist-info/RECORD
