Metadata-Version: 2.1
Name: siege-engine
Version: 3.0
Summary: Basically a SYN flooder in Python
Home-page: https://github.com/smok-serwis/siege-engine
Author: Piotr Maślanka
Author-email: pmaslanka@smok.co
License: UNKNOWN
Keywords: ha,high availability,scalable,scalability,server,metrics,tracing
Platform: UNKNOWN
Requires-Python: !=2.7.*,!=3.0.*,!=3.1.*,!=3.2.*,!=3.3.*,!=3.4.*
